package_notification/__init__.py
package_notification/notifications.py
package_notification-0.1.0.dist-info/LICENSE
package_notification-0.1.0.dist-info/METADATA
package_notification-0.1.0.dist-info/WHEEL
package_notification-0.1.0.dist-info/top_level.txt
package_notification-0.1.0.dist-info/RECORD
